State_Machine.v
//Main State Machine Implementation for S-Machine CPU
//By Duncan Cameron and Jasper Grant
//B00819540, B00829263 
//2023-11-07

/*
States:
    S0:enable
        Set start = 0

        if Enable = 1 move to state S1
        if Enable = 0 stay at state S0

    S1:Handle
        Set start = 1
        Increment count

        If done=0 go to S2
        If done=1 stay as S1

    S2:Notdone
        Set start = 0

        If done=0 stay
        if done =1 go to S1

*/

module StateMachine(enable,done,start,count);
    input enable, done;	
    output reg start;
	output reg [7:0] count;	
	//reg O;	
	reg [2:0] state;

    parameter s0 = 2'b00,	                
              s1 = 2'b01,			  
	 	      s2 = 2'b10;

	initial begin
		state = s0;
		count = 0;
		start = 0;
	end

    always@(done)	
	begin	      
		  begin		   
		    case(state)
            s0:			 
			  begin		               				
				if(enable == 1'b1) begin			  
					state <= s1;
				end			
				else begin				  
				    state <= s0;    
			  	end                      
			   end
			   
			s1:			 
			  begin
                  start <= 1'b1;
				  #1
				  start <= 1'b0;			               	
                  count = count+1;

				  if(done == 1'b1) begin			  
				    state <= s1;
				  end			
				  else begin
				    state <= s2;
				  end                    
			   end
			   
			s2:			 
			  begin		 
                 start <= 1'b0;	        //reset start since we don't want it to start       				
				  if(done == 1'b1) begin			  
				    state <= s1;	   // If done received go back to s1
				  end	
				  else begin
				    state <= s2;       //stay in s2 if done not received  
				  end                 
			   end
               endcase
		end
	end
        	
endmodule
/*
module moore_machine(clk,rst,I,O);  
    input  clk,rst,I;	
	output O;	
	reg O;	
	reg [2:0] state;
	
	parameter s0 = 3'b000,	                
              	  s1 = 3'b001,			  
	 	  s2 = 3'b010,			  
		  s3 = 3'b011,			  
		  s4 = 3'b100;
			  
	always@(posedge clk or posedge rst)	
	begin	    
	    if(rst == 1'b1)		  
		  begin		        
		    state <= s0;			
		    O  <= 1'b0;		  
		  end
		else 		  
		  begin		   
		    case(state)
			s0:			 
			  begin		               
     		      O <= 1'b0; 				
				  if(I == 1'b1)				  
				    state <= s0;				
				  else				  
				    state <= s1;                          
			   end
			   
			s1:			 
			  begin		               
     		      O <= 1'b0; 				
				  if(I == 1'b1)				  
				    state <= s2;				
				  else				  
				    state <= s1;                          
			   end
			   
			s2:			 
			  begin		               
     		      O <= 1'b0; 				
				  if(I == 1'b1)				  
				    state <= s0;				
				  else				  
				    state <= s3;                          
			   end
			   
			s3:			 
			  begin		               
     		      O <= 1'b0; 				
				  if(I == 1'b1)				  
				    state <= s4;				
				  else				  
				    state <= s1;                          
			   end
			   
			s4:			 
			  begin		               
     		      O <= 1'b1; 				
				  if(I == 1'b1)				  
				    state <= s0;				
				  else				  
				    state <= s1;                          
			   end
			endcase
		end
	end
endmodule
*/

Inst_Interpreter.v
//Instruction Interpreter Implementation for S-Machine CPU
//By Duncan Cameron and Jasper Grant
//B00829263
//2023-10-31

module InstInterpreter (
    input [15:0] inst,
    input start,

    input [15:0] data_in_memory,
    output reg read_write_memory,
    output reg [15:0] data_out_memory,
    output reg [7:0] addr,

    output reg done,
    output reg [7:0] PC

);

    //Declare status bits
    reg Z = 0, N = 0, C = 0;

    //Declare A and B registers
    reg [15:0] register_A;
  	reg [15:0] register_B;

    reg [15:0] register_temp = 0;

    reg [7:0] carry_matrix = 8'b00101011;// TODO: Could this be a parameter?

    initial begin
      	register_A = 0;
      	register_B = 0;
        PC = 0;
    end

    //On every instruction input change decide which logic should be followed
    always @(inst, posedge start) begin
        PC = PC + 1;
        //Store backup for register A in temp
        register_temp = register_A;
      
        case(inst[15:12])
            4'b0010: //INC instruction
            begin
                //TODO: check if 2s complement is needed to handle negatives
                if(inst[11]) begin
                    register_B = register_B + inst[7:0];
                end
                else begin
                    register_A = register_A + inst[7:0];
                end
                //Standard set ZNC bits
                Z = register_A == 0;
                N = register_A[15];
                C = carry_matrix[{register_temp[15], register_B[15], register_A[15]}];
            end
            4'b0100: //ADD instruction
            begin
                register_A = register_A + register_B;
                //Standard set ZNC bits
                Z = register_A == 0;
                N = register_A[15];
                C = carry_matrix[{register_temp[15], register_B[15], register_A[15]}];
            end
            4'b0101: //SUB instruction
            begin
                register_A = register_A - register_B;
                //Standard set ZNC bits
                Z = register_A == 0;
                N = register_A[15];
                C = carry_matrix[{register_temp[15], register_B[15], register_A[15]}];
            end
            4'b0110: //OR instruction
            begin
                register_A = register_A | register_B;
                //Standard set ZNC bits
                Z = register_A == 0;
                N = register_A[15];
                C = carry_matrix[{register_temp[15], register_B[15], register_A[15]}];
            end
            4'b0111: //AND instruction
            begin
                register_A = register_A & register_B;
                //Standard set ZNC bits
                Z = register_A == 0;
                N = register_A[15];
                C = carry_matrix[{register_temp[15], register_B[15], register_A[15]}];
            end
            4'b1000: //XOR instruction
            begin
                register_A = register_A ^ register_B;
                //Standard set ZNC bits
                Z = register_A == 0;
                N = register_A[15];
                C = carry_matrix[{register_temp[15], register_B[15], register_A[15]}];
            end
            4'b1001: //SHR instruction
            begin
                //Carry bit recieves value of reg_A[0]
                C = register_A[0];
                //Add 0 as [15] and then put digits 15-1 into spots 14-0
                register_A = {1'b0, register_A[15:1]};
            end
            4'b1010: //MOV instruction
            begin
                //Move register A to B
                register_B = register_A;
            end
            4'b1011: //EXCH instruction
            begin
                //A and B register values are swapped. Temp register is already equal to previous value of A
                register_A = register_B;
                register_B = register_temp;
                //Status bits remain the same
            end
            4'b1100: //CMP instruction
            begin
                //Perform subtraction with discarded output
                register_temp = register_A - register_B;
                //Standard set ZNC bits
                Z = register_A == 0;
                N = register_A[15];
                C = carry_matrix[{register_A[15], register_B[15], register_temp[15]}];
            end
            4'b1101: //SET instruction
            begin
                //Set bits based on set bits in inst
                Z = inst[10] ? 1 : Z;
                N = inst[9] ? 1 : N;
                C = inst[8] ? 1 : C;
            end
            4'b1110: //CLR instruction
            begin
                //Clear bits based on set bits in inst
                Z = inst[10] ? 0 : Z;
                N = inst[9] ? 0 : N;
                C = inst[8] ? 0 : C;
            end
            4'b0000: //LD instruction
            begin
                if(inst[11]) begin
                    if(inst[10]) begin
                      register_B = inst[9] ? {inst[7:0], 8'b00000000} : {8'b00000000, inst[7:0]};
                    end
                    else begin
                        //Fool with timing
                        read_write_memory = 0;
                        addr = inst[7:0];
                        register_B = data_in_memory;
                    end
                end
                else begin
                    if(inst[10]) begin
                      register_A = inst[9] ? {inst[7:0], 8'b00000000} : {8'b00000000, inst[7:0]};
                    end
                    else begin
                        //Fool with timing
                        read_write_memory = 0;
                        addr = inst[7:0];
                        register_A = data_in_memory;
                    end
                end
            end
            4'b0001: //ST instruction
            begin
                read_write_memory = 1;
                addr = inst[7:0];
                data_out_memory = inst[11] ? register_B : register_A;
            end
        endcase
        //Flash done
        done = 1;
      	#1
      	done = 0;
    end
    
endmodule

CPU.v
//CPU Implementation for S-Machine CPU
//By Duncan Cameron and Jasper Grant
//B00819540, B00829263 
//2023-11-07

`include "Inst_Interpreter.v"
`include "State_Machine.v"

module CPU(
    input [15:0] inst,

    input enable,

    input [15:0] data_in_memory,
    output read_write_memory,
    output [7:0] addr,
    output [15:0] data_out_memory,

    output [7:0] PC,

    output [7:0] count
);

    wire done;
    wire start;


InstInterpreter interpreter(
    .inst(inst),

    .data_in_memory(data_in_memory),
    .read_write_memory(read_write_memory),
    .data_out_memory(data_out_memory),
    .addr(addr),

    .done(done),
    .PC(PC)
);

StateMachine fsm(
    .start(start),
    .done(done),
    .enable(enable),
    .count(count)
);

endmodule

CPU.Test_Bench.v
//CPU Test Bench Implementation for S-Machine CPU
//By Duncan Cameron and Jasper Grant
//B00819540, B00829263 
//2023-11-07

`timescale 1ns / 1ns

module test_CPU;

    reg [15:0] inst;

    reg enable;

    reg [15:0] data_in_memory;
    wire read_write_memory;
    wire [7:0] addr;

    wire [7:0] PC;

    wire [7:0] count;

    CPU CPU(
        .inst(inst),
        .enable(enable),
        .data_in_memory(data_in_memory),
        .read_write_memory(read_write_memory),
        .addr(addr),
        .data_out_memory(data_out_memory),
        .PC(PC),
        .count(count)
    );

    initial begin
        $dumpfile("wave.vcd");
        $dumpvars(0, test_CPU);

    #1
    enable = 1;
    //Test 1: Load value from immediate
    #5
    inst = 16'b0000010000000001;
    #5
    inst = 16'b0000110000000001;
    //Test 2: Add values of registers
    #5
    inst = 16'b0100000000000000;
    //Test 3: Subtract value of registers
    #5
    inst = 16'b0101000000000000;
    //Test 4: INC register B
    #5
    inst = 16'b0010100000000001;
    //Test 5: OR value of registers
    #5
    inst = 16'b0110000000000000;
    //Test 6: AND value of registers
    #5
    inst = 16'b0111000000000000;
    //Test 7: XOR value of registers
    #5
    inst = 16'b1000000000000000;
    #5
      ;


    end


endmodule

wave.vcd
$date
	Thu Nov 16 17:34:51 2023
$end
$version
	ModelSim Version 10.5b
$end
$timescale
	1ns
$end

$scope module test_CPU $end
$var reg 16 ! inst [15:0] $end
$var reg 1 " enable $end
$var reg 16 # data_in_memory [15:0] $end
$var wire 1 $ read_write_memory $end
$var wire 1 % addr [7] $end
$var wire 1 & addr [6] $end
$var wire 1 ' addr [5] $end
$var wire 1 ( addr [4] $end
$var wire 1 ) addr [3] $end
$var wire 1 * addr [2] $end
$var wire 1 + addr [1] $end
$var wire 1 , addr [0] $end
$var wire 1 - PC [7] $end
$var wire 1 . PC [6] $end
$var wire 1 / PC [5] $end
$var wire 1 0 PC [4] $end
$var wire 1 1 PC [3] $end
$var wire 1 2 PC [2] $end
$var wire 1 3 PC [1] $end
$var wire 1 4 PC [0] $end
$var wire 1 5 count [7] $end
$var wire 1 6 count [6] $end
$var wire 1 7 count [5] $end
$var wire 1 8 count [4] $end
$var wire 1 9 count [3] $end
$var wire 1 : count [2] $end
$var wire 1 ; count [1] $end
$var wire 1 < count [0] $end
$var wire 1 = data_out_memory $end

$scope module CPU $end
$var wire 1 > inst [15] $end
$var wire 1 ? inst [14] $end
$var wire 1 @ inst [13] $end
$var wire 1 A inst [12] $end
$var wire 1 B inst [11] $end
$var wire 1 C inst [10] $end
$var wire 1 D inst [9] $end
$var wire 1 E inst [8] $end
$var wire 1 F inst [7] $end
$var wire 1 G inst [6] $end
$var wire 1 H inst [5] $end
$var wire 1 I inst [4] $end
$var wire 1 J inst [3] $end
$var wire 1 K inst [2] $end
$var wire 1 L inst [1] $end
$var wire 1 M inst [0] $end
$var wire 1 N enable $end
$var wire 1 O data_in_memory [15] $end
$var wire 1 P data_in_memory [14] $end
$var wire 1 Q data_in_memory [13] $end
$var wire 1 R data_in_memory [12] $end
$var wire 1 S data_in_memory [11] $end
$var wire 1 T data_in_memory [10] $end
$var wire 1 U data_in_memory [9] $end
$var wire 1 V data_in_memory [8] $end
$var wire 1 W data_in_memory [7] $end
$var wire 1 X data_in_memory [6] $end
$var wire 1 Y data_in_memory [5] $end
$var wire 1 Z data_in_memory [4] $end
$var wire 1 [ data_in_memory [3] $end
$var wire 1 \ data_in_memory [2] $end
$var wire 1 ] data_in_memory [1] $end
$var wire 1 ^ data_in_memory [0] $end
$var wire 1 $ read_write_memory $end
$var wire 1 % addr [7] $end
$var wire 1 & addr [6] $end
$var wire 1 ' addr [5] $end
$var wire 1 ( addr [4] $end
$var wire 1 ) addr [3] $end
$var wire 1 * addr [2] $end
$var wire 1 + addr [1] $end
$var wire 1 , addr [0] $end
$var wire 1 _ data_out_memory [15] $end
$var wire 1 ` data_out_memory [14] $end
$var wire 1 a data_out_memory [13] $end
$var wire 1 b data_out_memory [12] $end
$var wire 1 c data_out_memory [11] $end
$var wire 1 d data_out_memory [10] $end
$var wire 1 e data_out_memory [9] $end
$var wire 1 f data_out_memory [8] $end
$var wire 1 g data_out_memory [7] $end
$var wire 1 h data_out_memory [6] $end
$var wire 1 i data_out_memory [5] $end
$var wire 1 j data_out_memory [4] $end
$var wire 1 k data_out_memory [3] $end
$var wire 1 l data_out_memory [2] $end
$var wire 1 m data_out_memory [1] $end
$var wire 1 = data_out_memory [0] $end
$var wire 1 - PC [7] $end
$var wire 1 . PC [6] $end
$var wire 1 / PC [5] $end
$var wire 1 0 PC [4] $end
$var wire 1 1 PC [3] $end
$var wire 1 2 PC [2] $end
$var wire 1 3 PC [1] $end
$var wire 1 4 PC [0] $end
$var wire 1 5 count [7] $end
$var wire 1 6 count [6] $end
$var wire 1 7 count [5] $end
$var wire 1 8 count [4] $end
$var wire 1 9 count [3] $end
$var wire 1 : count [2] $end
$var wire 1 ; count [1] $end
$var wire 1 < count [0] $end
$var wire 1 n done $end
$var wire 1 o start $end

$scope module interpreter $end
$var wire 1 > inst [15] $end
$var wire 1 ? inst [14] $end
$var wire 1 @ inst [13] $end
$var wire 1 A inst [12] $end
$var wire 1 B inst [11] $end
$var wire 1 C inst [10] $end
$var wire 1 D inst [9] $end
$var wire 1 E inst [8] $end
$var wire 1 F inst [7] $end
$var wire 1 G inst [6] $end
$var wire 1 H inst [5] $end
$var wire 1 I inst [4] $end
$var wire 1 J inst [3] $end
$var wire 1 K inst [2] $end
$var wire 1 L inst [1] $end
$var wire 1 M inst [0] $end
$var wire 1 o start $end
$var wire 1 O data_in_memory [15] $end
$var wire 1 P data_in_memory [14] $end
$var wire 1 Q data_in_memory [13] $end
$var wire 1 R data_in_memory [12] $end
$var wire 1 S data_in_memory [11] $end
$var wire 1 T data_in_memory [10] $end
$var wire 1 U data_in_memory [9] $end
$var wire 1 V data_in_memory [8] $end
$var wire 1 W data_in_memory [7] $end
$var wire 1 X data_in_memory [6] $end
$var wire 1 Y data_in_memory [5] $end
$var wire 1 Z data_in_memory [4] $end
$var wire 1 [ data_in_memory [3] $end
$var wire 1 \ data_in_memory [2] $end
$var wire 1 ] data_in_memory [1] $end
$var wire 1 ^ data_in_memory [0] $end
$var reg 1 p read_write_memory $end
$var reg 16 q data_out_memory [15:0] $end
$var reg 8 r addr [7:0] $end
$var reg 1 s done $end
$var reg 8 t PC [7:0] $end
$var reg 1 u Z $end
$var reg 1 v N $end
$var reg 1 w C $end
$var reg 16 x register_A [15:0] $end
$var reg 16 y register_B [15:0] $end
$var reg 16 z register_temp [15:0] $end
$var reg 8 { carry_matrix [7:0] $end
$upscope $end

$scope module fsm $end
$var parameter 2 | s0 $end
$var parameter 2 } s1 $end
$var parameter 2 ~ s2 $end
$var wire 1 N enable $end
$var wire 1 n done $end
$var reg 1 !! start $end
$var reg 8 "! count [7:0] $end
$var reg 3 #! state [2:0] $end
$upscope $end
$upscope $end
$upscope $end
$enddefinitions $end
#0
$dumpvars
bx !
x"
bx #
xp
bx q
bx r
xs
bx t
0u
0v
0w
bx x
bx y
b0 z
b101011 {
0!!
b0 "!
b0 #!
b0 |
b1 }
b10 ~
x$
x,
x+
x*
x)
x(
x'
x&
x%
x4
x3
x2
x1
x0
x/
x.
x-
0<
0;
0:
09
08
07
06
05
x=
xn
0o
x^
x]
x\
x[
xZ
xY
xX
xW
xV
xU
xT
xS
xR
xQ
xP
xO
xN
xM
xL
xK
xJ
xI
xH
xG
xF
xE
xD
xC
xB
xA
x@
x?
x>
xm
xl
xk
xj
xi
xh
xg
xf
xe
xd
xc
xb
xa
x`
x_
$end
#1
1"
1N
#2
b0 x
b0 y
b0 t
0s
04
03
02
01
00
0/
0.
0-
0n
b1 #!
#6
b10000000001 !
1M
0L
0K
0J
0I
0H
0G
0F
0E
0D
1C
0B
0A
0@
0?
0>
#7
b1 t
b1 x
1s
14
1n
1!!
1o
#9
0s
b1 "!
1<
0n
0!!
1!!
#11
b110000000001 !
b10 "!
0<
1;
1B
0!!
b10 #!
0o
#12
b10 t
b1 z
b1 y
1s
04
13
1n
b1 #!
#14
0s
0n
1!!
1o
#15
b11 t
1s
14
1n
#16
b100000000000000 !
b11 "!
1<
0M
0C
0B
1?
0!!
0o
#17
0s
0n
1!!
1o
#18
b100 t
b10 x
1w
1s
04
03
12
1n
#19
b100 "!
0<
0;
1:
0!!
0o
#20
0s
0n
1!!
1o
#21
b101000000000000 !
b101 t
b10 z
b11 x
1s
14
1A
1n
#22
b101 "!
1<
0!!
0o
#23
0s
0n
1!!
1o
#24
b110 t
b11 z
b10 x
1s
04
13
1n
#25
b110 "!
0<
1;
0!!
0o
#26
b10100000000001 !
0s
1M
1B
0A
1@
0?
0n
1!!
1o
#27
b111 t
b10 z
b10 y
1s
14
1n
#28
b111 "!
1<
0!!
0o
#29
0s
0n
1!!
1o
#30
b1000 t
b11 y
1s
04
03
02
11
1n
#31
b110000000000000 !
b1000 "!
0<
0;
0:
19
0M
0B
1?
0!!
0o
#32
0s
0n
1!!
1o
#33
b1001 t
b11 x
1s
14
1n
#34
b1001 "!
1<
0!!
0o
#35
0s
0n
1!!
1o
#36
b111000000000000 !
b1010 t
b11 z
1s
04
13
1A
1n
#37
b1010 "!
0<
1;
0!!
0o
#38
0s
0n
1!!
1o
#39
b1011 t
1s
14
1n
#40
b1011 "!
1<
0!!
0o
#41
b1000000000000000 !
0s
0A
0@
0?
1>
0n
1!!
1o
#42
b1100 t
b0 x
1u
1s
04
03
12
1n
#43
b1100 "!
0<
0;
1:
0!!
0o
#44
0s
0n
1!!
1o
#45
b1101 t
b0 z
b11 x
0u
1s
14
1n
#46
b1101 "!
1<
0!!
0o
#47
0s
0n
1!!
1o
#48
b1110 t
b11 z
b0 x
1u
1s
04
13
1n
#49
b1110 "!
0<
1;
0!!
0o
#50
0s
0n
1!!
1o
#51
b1111 t
b0 z
b11 x
0u
1s
14
1n
#52
b1111 "!
1<
0!!
0o
#53
0s
0n
1!!
1o
#54
b10000 t
b11 z
b0 x
1u
1s
04
03
02
01
10
1n
#55
b10000 "!
0<
0;
0:
09
18
0!!
0o
#56
0s
0n
1!!
1o
#57
b10001 t
b0 z
b11 x
0u
1s
14
1n
#58
b10001 "!
1<
0!!
0o
#59
0s
0n
1!!
1o
#60
b10010 t
b11 z
b0 x
1u
1s
04
13
1n
#61
b10010 "!
0<
1;
0!!
0o
#62
0s
0n
1!!
1o
#63
b10011 t
b0 z
b11 x
0u
1s
14
1n
#64
b10011 "!
1<
0!!
0o
#65
0s
0n
1!!
1o
#66
b10100 t
b11 z
b0 x
1u
1s
04
03
12
1n
#67
b10100 "!
0<
0;
1:
0!!
0o
#68
0s
0n
1!!
1o
#69
b10101 t
b0 z
b11 x
0u
1s
14
1n
#70
b10101 "!
1<
0!!
0o
#71
0s
0n
1!!
1o
#72
b10110 t
b11 z
b0 x
1u
1s
04
13
1n
#73
b10110 "!
0<
1;
0!!
0o
#74
0s
0n
1!!
1o
#75
b10111 t
b0 z
b11 x
0u
1s
14
1n
#76
b10111 "!
1<
0!!
0o
#77
0s
0n
1!!
1o
#78
b11000 t
b11 z
b0 x
1u
1s
04
03
02
11
1n
#79
b11000 "!
0<
0;
0:
19
0!!
0o
#80
0s
0n
1!!
1o
#81
b11001 t
b0 z
b11 x
0u
1s
14
1n
#82
b11001 "!
1<
0!!
0o
#83
0s
0n
1!!
1o
#84
b11010 t
b11 z
b0 x
1u
1s
04
13
1n
#85
b11010 "!
0<
1;
0!!
0o
#86
0s
0n
1!!
1o
#87
b11011 t
b0 z
b11 x
0u
1s
14
1n
#88
b11011 "!
1<
0!!
0o
#89
0s
0n
1!!
1o
#90
b11100 t
b11 z
b0 x
1u
1s
04
03
12
1n
#91
b11100 "!
0<
0;
1:
0!!
0o
#92
0s
0n
1!!
1o
#93
b11101 t
b0 z
b11 x
0u
1s
14
1n
#94
b11101 "!
1<
0!!
0o
#95
0s
0n
1!!
1o
#96
b11110 t
b11 z
b0 x
1u
1s
04
13
1n
#97
b11110 "!
0<
1;
0!!
0o
#98
0s
0n
1!!
1o
#99
b11111 t
b0 z
b11 x
0u
1s
14
1n
#100
b11111 "!
1<
0!!
0o
#101
0s
0n
1!!
1o
#102
b100000 t
b11 z
b0 x
1u
1s
04
03
02
01
00
1/
1n
#103
b100000 "!
0<
0;
0:
09
08
17
0!!
0o
#104
0s
0n
1!!
1o
#105
b100001 t
b0 z
b11 x
0u
1s
14
1n
#106
b100001 "!
1<
0!!
0o
#107
0s
0n
1!!
1o
#108
b100010 t
b11 z
b0 x
1u
1s
04
13
1n
#109
b100010 "!
0<
1;
0!!
0o
#110
0s
0n
1!!
1o
#111
b100011 t
b0 z
b11 x
0u
1s
14
1n
#112
b100011 "!
1<
0!!
0o
#113
0s
0n
1!!
1o
#114
b100100 t
b11 z
b0 x
1u
1s
04
03
12
1n
#115
b100100 "!
0<
0;
1:
0!!
0o
#116
0s
0n
1!!
1o
#117
b100101 t
b0 z
b11 x
0u
1s
14
1n
#118
b100101 "!
1<
0!!
0o
#119
0s
0n
1!!
1o
#120
b100110 t
b11 z
b0 x
1u
1s
04
13
1n
#121
b100110 "!
0<
1;
0!!
0o
#122
0s
0n
1!!
1o
#123
b100111 t
b0 z
b11 x
0u
1s
14
1n
#124
b100111 "!
1<
0!!
0o
#125
0s
0n
1!!
1o
#126
b101000 t
b11 z
b0 x
1u
1s
04
03
02
11
1n
#127
b101000 "!
0<
0;
0:
19
0!!
0o
#128
0s
0n
1!!
1o
#129
b101001 t
b0 z
b11 x
0u
1s
14
1n
#130
b101001 "!
1<
0!!
0o
#131
0s
0n
1!!
1o
#132
b101010 t
b11 z
b0 x
1u
1s
04
13
1n
#133
b101010 "!
0<
1;
0!!
0o
#134
0s
0n
1!!
1o
#135
b101011 t
b0 z
b11 x
0u
1s
14
1n
#136
b101011 "!
1<
0!!
0o
#137
0s
0n
1!!
1o
#138
b101100 t
b11 z
b0 x
1u
1s
04
03
12
1n
#139
b101100 "!
0<
0;
1:
0!!
0o
#140
0s
0n
1!!
1o
#141
b101101 t
b0 z
b11 x
0u
1s
14
1n
#142
b101101 "!
1<
0!!
0o
#143
0s
0n
1!!
1o
#144
b101110 t
b11 z
b0 x
1u
1s
04
13
1n
#145
b101110 "!
0<
1;
0!!
0o
#146
0s
0n
1!!
1o
#147
b101111 t
b0 z
b11 x
0u
1s
14
1n
#148
b101111 "!
1<
0!!
0o
#149
0s
0n
1!!
1o
#150
b110000 t
b11 z
b0 x
1u
1s
04
03
02
01
10
1n
#151
b110000 "!
0<
0;
0:
09
18
0!!
0o
#152
0s
0n
1!!
1o
#153
b110001 t
b0 z
b11 x
0u
1s
14
1n
#154
b110001 "!
1<
0!!
0o
#155
0s
0n
1!!
1o
#156
b110010 t
b11 z
b0 x
1u
1s
04
13
1n
#157
b110010 "!
0<
1;
0!!
0o
#158
0s
0n
1!!
1o
#159
b110011 t
b0 z
b11 x
0u
1s
14
1n
#160
b110011 "!
1<
0!!
0o
#161
0s
0n
1!!
1o
#162
b110100 t
b11 z
b0 x
1u
1s
04
03
12
1n
#163
b110100 "!
0<
0;
1:
0!!
0o
#164
0s
0n
1!!
1o
#165
b110101 t
b0 z
b11 x
0u
1s
14
1n
#166
b110101 "!
1<
0!!
0o
#167
0s
0n
1!!
1o
#168
b110110 t
b11 z
b0 x
1u
1s
04
13
1n
#169
b110110 "!
0<
1;
0!!
0o
#170
0s
0n
1!!
1o
#171
b110111 t
b0 z
b11 x
0u
1s
14
1n
#172
b110111 "!
1<
0!!
0o
#173
0s
0n
1!!
1o
#174
b111000 t
b11 z
b0 x
1u
1s
04
03
02
11
1n
#175
b111000 "!
0<
0;
0:
19
0!!
0o
#176
0s
0n
1!!
1o
#177
b111001 t
b0 z
b11 x
0u
1s
14
1n
#178
b111001 "!
1<
0!!
0o
#179
0s
0n
1!!
1o
#180
b111010 t
b11 z
b0 x
1u
1s
04
13
1n
#181
b111010 "!
0<
1;
0!!
0o
#182
0s
0n
1!!
1o
#183
b111011 t
b0 z
b11 x
0u
1s
14
1n
#184
b111011 "!
1<
0!!
0o
#185
0s
0n
1!!
1o
#186
b111100 t
b11 z
b0 x
1u
1s
04
03
12
1n
#187
b111100 "!
0<
0;
1:
0!!
0o
#188
0s
0n
1!!
1o
#189
b111101 t
b0 z
b11 x
0u
1s
14
1n
#190
b111101 "!
1<
0!!
0o
#191
0s
0n
1!!
1o
#192
b111110 t
b11 z
b0 x
1u
1s
04
13
1n
#193
b111110 "!
0<
1;
0!!
0o
#194
0s
0n
1!!
1o
#195
b111111 t
b0 z
b11 x
0u
1s
14
1n
#196
b111111 "!
1<
0!!
0o
#197
0s
0n
1!!
1o
#198
b1000000 t
b11 z
b0 x
1u
1s
04
03
02
01
00
0/
1.
1n
#199
b1000000 "!
0<
0;
0:
09
08
07
16
0!!
0o
#200
0s
0n
1!!
1o
#201
b1000001 t
b0 z
b11 x
0u
1s
14
1n
#202
b1000001 "!
1<
0!!
0o
#203
0s
0n
1!!
1o
#204
b1000010 t
b11 z
b0 x
1u
1s
04
13
1n
#205
b1000010 "!
0<
1;
0!!
0o
#206
0s
0n
1!!
1o
#207
b1000011 t
b0 z
b11 x
0u
1s
14
1n
#208
b1000011 "!
1<
0!!
0o
#209
0s
0n
1!!
1o
#210
b1000100 t
b11 z
b0 x
1u
1s
04
03
12
1n
#211
b1000100 "!
0<
0;
1:
0!!
0o
#212
0s
0n
1!!
1o
#213
b1000101 t
b0 z
b11 x
0u
1s
14
1n
#214
b1000101 "!
1<
0!!
0o
#215
0s
0n
1!!
1o
#216
b1000110 t
b11 z
b0 x
1u
1s
04
13
1n
#217
b1000110 "!
0<
1;
0!!
0o
#218
0s
0n
1!!
1o
#219
b1000111 t
b0 z
b11 x
0u
1s
14
1n
#220
b1000111 "!
1<
0!!
0o
#221
0s
0n
1!!
1o
#222
b1001000 t
b11 z
b0 x
1u
1s
04
03
02
11
1n
#223
b1001000 "!
0<
0;
0:
19
0!!
0o
#224
0s
0n
1!!
1o
#225
b1001001 t
b0 z
b11 x
0u
1s
14
1n
#226
b1001001 "!
1<
0!!
0o
#227
0s
0n
1!!
1o
#228
b1001010 t
b11 z
b0 x
1u
1s
04
13
1n
#229
b1001010 "!
0<
1;
0!!
0o
#230
0s
0n
1!!
1o
#231
b1001011 t
b0 z
b11 x
0u
1s
14
1n
#232
b1001011 "!
1<
0!!
0o
#233
0s
0n
1!!
1o
#234
b1001100 t
b11 z
b0 x
1u
1s
04
03
12
1n
#235
b1001100 "!
0<
0;
1:
0!!
0o
#236
0s
0n
1!!
1o
#237
b1001101 t
b0 z
b11 x
0u
1s
14
1n
#238
b1001101 "!
1<
0!!
0o
#239
0s
0n
1!!
1o
#240
b1001110 t
b11 z
b0 x
1u
1s
04
13
1n
#241
b1001110 "!
0<
1;
0!!
0o
#242
0s
0n
1!!
1o
#243
b1001111 t
b0 z
b11 x
0u
1s
14
1n
#244
b1001111 "!
1<
0!!
0o
#245
0s
0n
1!!
1o
#246
b1010000 t
b11 z
b0 x
1u
1s
04
03
02
01
10
1n
#247
b1010000 "!
0<
0;
0:
09
18
0!!
0o
#248
0s
0n
1!!
1o
#249
b1010001 t
b0 z
b11 x
0u
1s
14
1n
#250
b1010001 "!
1<
0!!
0o
#251
0s
0n
1!!
1o
#252
b1010010 t
b11 z
b0 x
1u
1s
04
13
1n
#253
b1010010 "!
0<
1;
0!!
0o
#254
0s
0n
1!!
1o
#255
b1010011 t
b0 z
b11 x
0u
1s
14
1n
#256
b1010011 "!
1<
0!!
0o
#257
0s
0n
1!!
1o
#258
b1010100 t
b11 z
b0 x
1u
1s
04
03
12
1n
#259
b1010100 "!
0<
0;
1:
0!!
0o
#260
0s
0n
1!!
1o
#261
b1010101 t
b0 z
b11 x
0u
1s
14
1n
#262
b1010101 "!
1<
0!!
0o
#263
0s
0n
1!!
1o
#264
b1010110 t
b11 z
b0 x
1u
1s
04
13
1n
#265
b1010110 "!
0<
1;
0!!
0o
#266
0s
0n
1!!
1o
#267
b1010111 t
b0 z
b11 x
0u
1s
14
1n
#268
b1010111 "!
1<
0!!
0o
#269
0s
0n
1!!
1o
#270
b1011000 t
b11 z
b0 x
1u
1s
04
03
02
11
1n
#271
b1011000 "!
0<
0;
0:
19
0!!
0o
#272
0s
0n
1!!
1o
#273
b1011001 t
b0 z
b11 x
0u
1s
14
1n
#274
b1011001 "!
1<
0!!
0o
#275
0s
0n
1!!
1o
#276
b1011010 t
b11 z
b0 x
1u
1s
04
13
1n
#277
b1011010 "!
0<
1;
0!!
0o
#278
0s
0n
1!!
1o
#279
b1011011 t
b0 z
b11 x
0u
1s
14
1n
#280
b1011011 "!
1<
0!!
0o
#281
0s
0n
1!!
1o
#282
b1011100 t
b11 z
b0 x
1u
1s
04
03
12
1n
#283
b1011100 "!
0<
0;
1:
0!!
0o
#284
0s
0n
1!!
1o
#285
b1011101 t
b0 z
b11 x
0u
1s
14
1n
#286
b1011101 "!
1<
0!!
0o
#287
0s
0n
1!!
1o
#288
b1011110 t
b11 z
b0 x
1u
1s
04
13
1n
#289
b1011110 "!
0<
1;
0!!
0o
#290
0s
0n
1!!
1o
#291
b1011111 t
b0 z
b11 x
0u
1s
14
1n
#292
b1011111 "!
1<
0!!
0o
#293
0s
0n
1!!
1o
#294
b1100000 t
b11 z
b0 x
1u
1s
04
03
02
01
00
1/
1n
#295
b1100000 "!
0<
0;
0:
09
08
17
0!!
0o
#296
0s
0n
1!!
1o
#297
b1100001 t
b0 z
b11 x
0u
1s
14
1n
#298
b1100001 "!
1<
0!!
0o
#299
0s
0n
1!!
1o
#300
b1100010 t
b11 z
b0 x
1u
1s
04
13
1n
